asciinema_scene/.DS_Store
asciinema_scene/__init__.py
asciinema_scene/scenelib/__init__.py
asciinema_scene/scenelib/constants.py
asciinema_scene/scenelib/frame.py
asciinema_scene/scenelib/scene.py
asciinema_scene/scenelib/scene_content.py
asciinema_scene/scenelib/utils.py
asciinema_scene/sciine.py
asciinema_scene-1.2.2.dist-info/WHEEL
asciinema_scene-1.2.2.dist-info/entry_points.txt
asciinema_scene-1.2.2.dist-info/METADATA
asciinema_scene-1.2.2.dist-info/RECORD
