Metadata-Version: 2.4
Name: asciinema-scene
Version: 1.2.2
Summary: Toolbox to edit asciinema screencasts (sciine)
Author: Jerome Dumonteil
Author-email: Jerome Dumonteil <jerome.dumonteil@gmail.com>
License-Expression: MIT
Classifier: Development Status :: 5 - Production/Stable
Classifier: Environment :: Console
Classifier: Intended Audience :: Developers
Classifier: Programming Language :: Python :: 3.10
Classifier: Programming Language :: Python :: 3.11
Classifier: Programming Language :: Python :: 3.12
Classifier: Programming Language :: Python :: 3.13
Classifier: Programming Language :: Python :: 3.14
Requires-Dist: click>=8.3.0,<9
Requires-Python: >=3.10, <4.0
Project-URL: Changelog, https://github.com/jdum/asciinema-scene/blob/master/CHANGES.md
Project-URL: Documentation, https://jdum.github.io/asciinema-scene/
Project-URL: Repository, https://github.com/jdum/asciinema-scene
